sanctuary_system/__init__.py
sanctuary_system/mcp_server.py
sanctuary_system_mcp-0.2.0.dist-info/LICENSE
sanctuary_system_mcp-0.2.0.dist-info/METADATA
sanctuary_system_mcp-0.2.0.dist-info/WHEEL
sanctuary_system_mcp-0.2.0.dist-info/entry_points.txt
sanctuary_system_mcp-0.2.0.dist-info/top_level.txt
sanctuary_system_mcp-0.2.0.dist-info/RECORD
