Metadata-Version: 2.1
Name: sanctuary-system-mcp
Version: 0.2.0
Summary: Sanctuary System - Narrative wrapper and scoring for STARSYSTEM compound intelligence
Author: Isaac
License: GNOSYS Personal Builder License (GPBL) v1.0
Keywords: mcp ai sanctuary starsystem narrative mythology
Classifier: Development Status :: 3 - Alpha
Classifier: Intended Audience :: Developers
Classifier: Programming Language :: Python :: 3
Classifier: Programming Language :: Python :: 3.10
Classifier: Programming Language :: Python :: 3.11
Requires-Python: >=3.10
License-File: LICENSE
Requires-Dist: fastmcp>=2.0.0
Requires-Dist: heaven-framework>=0.1.0
